README.md
setup.py
infcli/__init__.py
infcli.egg-info/PKG-INFO
infcli.egg-info/SOURCES.txt
infcli.egg-info/dependency_links.txt
infcli.egg-info/not-zip-safe
infcli.egg-info/requires.txt
infcli.egg-info/top_level.txt
src/__init__.py
src/config.py
src/models.py
src/api/__init__.py
src/api/base.py
src/api/tests/__init__.py
src/api/tests/base.py
src/api/tests/test_api.py
src/tests/__init__.py
src/tests/base.py