Metadata-Version: 1.0
Name: infcli
Version: 1.0.0
Summary: Infinity Python Driver
Home-page: https://github.com/infamily/infinity-driver
Author: Mindey
Author-email: mindey@qq.com
License: UNLICENSE
Platform: UNKNOWN
